franknpython/__init__.py
franknpython/__main__.py
franknpython-0.1.1.dist-info/LICENSE
franknpython-0.1.1.dist-info/METADATA
franknpython-0.1.1.dist-info/WHEEL
franknpython-0.1.1.dist-info/RECORD
